funnumbers/__init__.py
funnumbers-0.1.dist-info/LICENSE.txt
funnumbers-0.1.dist-info/METADATA
funnumbers-0.1.dist-info/WHEEL
funnumbers-0.1.dist-info/top_level.txt
funnumbers-0.1.dist-info/RECORD
