Metadata-Version: 2.1
Name: funnumbers
Version: 0.1
Summary: This is a simple module
Author: Usama
Author-email: ubinkhalil11@gmail.com
Classifier: Programming Language :: Python :: 3
Classifier: License :: OSI Approved :: MIT License
Classifier: Operating System :: OS Independent
License-File: LICENSE.txt
